MANIFEST.in
README.md
setup.py
btchip/__init__.py
btchip/bitcoinTransaction.py
btchip/bitcoinVarint.py
btchip/btchip.py
btchip/btchipComm.py
btchip/btchipException.py
btchip/btchipFirmwareWizard.py
btchip/btchipHelpers.py
btchip/btchipKeyRecovery.py
btchip/btchipPersoWizard.py
btchip/btchipUtils.py
btchip/ledgerWrapper.py
btchip/msqr.py
btchip/ui/__init__.py
btchip/ui/personalization00start.py
btchip/ui/personalization01seed.py
btchip/ui/personalization02security.py
btchip/ui/personalization03config.py
btchip/ui/personalization04finalize.py
btchip/ui/personalizationseedbackup01.py
btchip/ui/personalizationseedbackup02.py
btchip/ui/personalizationseedbackup03.py
btchip/ui/personalizationseedbackup04.py
btchip_python_syscoin.egg-info/PKG-INFO
btchip_python_syscoin.egg-info/SOURCES.txt
btchip_python_syscoin.egg-info/dependency_links.txt
btchip_python_syscoin.egg-info/not-zip-safe
btchip_python_syscoin.egg-info/requires.txt
btchip_python_syscoin.egg-info/top_level.txt