Metadata-Version: 2.1
Name: btchip-python-syscoin
Version: 0.1.30
Summary: Python library to communicate with Ledger Nano dongle for Syscoin
Home-page: https://github.com/syscoin/btchip-python
Author: sidhujag
Author-email: sidhujag@gmail.com
License: UNKNOWN
Platform: UNKNOWN
Classifier: License :: OSI Approved :: Apache Software License
Classifier: Operating System :: POSIX :: Linux
Classifier: Operating System :: Microsoft :: Windows
Classifier: Operating System :: MacOS :: MacOS X
Provides-Extra: smartcard
